invokify/__init__.py
invokify/invokify.py
invokify/parser.py
invokify-0.1.4.dist-info/LICENSE
invokify-0.1.4.dist-info/METADATA
invokify-0.1.4.dist-info/WHEEL
invokify-0.1.4.dist-info/RECORD
