Metadata-Version: 2.3
Name: invokify
Version: 0.1.4
Summary: 
License: MIT
Author: iRedSC
Requires-Python: >=3.10,<4.0
Classifier: License :: OSI Approved :: MIT License
Classifier: Programming Language :: Python :: 3
Classifier: Programming Language :: Python :: 3.10
Classifier: Programming Language :: Python :: 3.11
Classifier: Programming Language :: Python :: 3.12
Classifier: Programming Language :: Python :: 3.13
Requires-Dist: tokenstream (>=1.5.0,<2.0.0)
